lifetimefitting/__init__.py
lifetimefitting/__main__.py
lifetimefitting/lifetimeGui.ui
lifetimefitting/funcs/__init__.py
lifetimefitting/funcs/expFuncs.py
lifetimefitting/funcs/fittingFuncs.py
lifetimefitting/funcs/gui.py
lifetimefitting-0.0.30.dist-info/LICENSE.md
lifetimefitting-0.0.30.dist-info/METADATA
lifetimefitting-0.0.30.dist-info/WHEEL
lifetimefitting-0.0.30.dist-info/top_level.txt
lifetimefitting-0.0.30.dist-info/RECORD
