Metadata-Version: 2.1
Name: lifetimefitting
Version: 0.0.30
Summary: PicoHarp TCSPC lifetime fitting tool
Home-page: https://github.com/adreasnow/LifetimeFittingTool
Author: Adrea Snow
Author-email: adrea.snow@gmail.com
Classifier: Programming Language :: Python :: 3
Classifier: License :: OSI Approved :: MIT License
Classifier: Operating System :: OS Independent
Requires-Python: >=3.8
License-File: LICENSE.md
Requires-Dist: matplotlib
Requires-Dist: numpy
Requires-Dist: scipy
Requires-Dist: pyqt6
Requires-Dist: phdimporter (>=0.0.3)
Provides-Extra: dev
Requires-Dist: twine (>=4.0.2) ; extra == 'dev'
